chapter4/delay_chain/DelayChain.sv
`ifndef __DELAY_CHAIN_SV__
`define __DELAY_CHAIN_SV__

module DelayChain #(
    parameter integer DW  = 8,
    parameter integer LEN = 4
) (
  input  wire               clk,
  input  wire               rst_n,
  input  wire               en,
  input  wire  [DW - 1 : 0] in,
  output logic [DW - 1 : 0] out
);

  generate
    if (LEN == 0) begin : g_zero_delay
      assign out = in;

    end else if (LEN == 1) begin : g_one_delay
      logic [DW - 1 : 0] dly;
      always_ff @(posedge clk, negedge rst_n) begin
        if (!rst_n) dly <= '0;
        else if (en) dly <= in;
      end
      assign out = dly;

    end else begin : g_delay
      logic [LEN - 1 : 0][DW - 1 : 0] dly;
      always_ff @(posedge clk, negedge rst_n) begin
        // if (!rst_n) dly <= '{LEN{'0}};
        // assign to a packed array
        if (!rst_n) dly <= '0;
        else if (en) dly[0+:LEN] <= {dly[0+:LEN-1], in};
      end
      assign out = dly[LEN-1];

    end
  endgenerate

endmodule

`endif

chapter4/delay_chain/TestDelayChain.sv
`timescale 1ns / 100ps
`include "./DelayChain.sv"

`default_nettype none

module TestDelayChain;
  initial begin
    $dumpfile("TestDelayChain.vcd");
    $dumpvars(0, TestDelayChain);
  end

  logic clk = 1'b0;
  logic rst_n = 1'b0;
  initial forever #5 clk = ~clk;
  initial #35 rst_n = 1'b1;
  initial #400 $finish;

  localparam integer DW = 8;
  logic [DW - 1 : 0] a, y;
  always #10 a <= DW'($urandom());

  DelayChain #(
      .DW(8),
      .LEN(5)
  ) dc (
      .clk  (clk),
      .rst_n(rst_n),
      .en   (1'b1),
      .in   (a),
      .out  (y)
  );

endmodule

chapter4/delay_chain/TestDelayChain.vcd
$date
	Mon Dec 16 17:32:58 2024
$end
$version
	Icarus Verilog
$end
$timescale
	100ps
$end
$scope module TestDelayChain $end
$var wire 8 ! y [7:0] $end
$var parameter 32 " DW $end
$var reg 8 # a [7:0] $end
$var reg 1 $ clk $end
$var reg 1 % rst_n $end
$scope module dc $end
$var wire 1 $ clk $end
$var wire 1 & en $end
$var wire 8 ' in [7:0] $end
$var wire 1 % rst_n $end
$var wire 8 ( out [7:0] $end
$var parameter 32 ) DW $end
$var parameter 32 * LEN $end
$scope begin g_delay $end
$var reg 40 + dly [39:0] $end
$upscope $end
$upscope $end
$upscope $end
$enddefinitions $end
$comment Show the parameter values. $end
$dumpall
b101 *
b1000 )
b1000 "
$end
#0
$dumpvars
bx +
bx (
bx '
1&
0%
0$
bx #
bx !
$end
#50
b0 !
b0 (
b0 +
1$
#100
b100100 #
b100100 '
0$
#150
1$
#200
b10000001 #
b10000001 '
0$
#250
1$
#300
b1001 #
b1001 '
0$
#350
b1001 +
1$
1%
#400
b1100011 #
b1100011 '
0$
#450
b100101100011 +
1$
#500
b1101 #
b1101 '
0$
#550
b10010110001100001101 +
1$
#600
b10001101 #
b10001101 '
0$
#650
b1001011000110000110110001101 +
1$
#700
b1100101 #
b1100101 '
0$
#750
b1001 !
b1001 (
b100101100011000011011000110101100101 +
1$
#800
b10010 #
b10010 '
0$
#850
b1100011 !
b1100011 (
b110001100001101100011010110010100010010 +
1$
#900
b1 #
b1 '
0$
#950
b1101 !
b1101 (
b110110001101011001010001001000000001 +
1$
#1000
b1101 #
b1101 '
0$
#1050
b10001101 !
b10001101 (
b1000110101100101000100100000000100001101 +
1$
#1100
b1110110 #
b1110110 '
0$
#1150
b1100101 !
b1100101 (
b110010100010010000000010000110101110110 +
1$
#1200
b111101 #
b111101 '
0$
#1250
b10010 !
b10010 (
b1001000000001000011010111011000111101 +
1$
#1300
b11101101 #
b11101101 '
0$
#1350
b1 !
b1 (
b100001101011101100011110111101101 +
1$
#1400
b10001100 #
b10001100 '
0$
#1450
b1101 !
b1101 (
b110101110110001111011110110110001100 +
1$
#1500
b11111001 #
b11111001 '
0$
#1550
b1110110 !
b1110110 (
b111011000111101111011011000110011111001 +
1$
#1600
b11000110 #
b11000110 '
0$
#1650
b111101 !
b111101 (
b11110111101101100011001111100111000110 +
1$
#1700
b11000101 #
b11000101 '
0$
#1750
b11101101 !
b11101101 (
b1110110110001100111110011100011011000101 +
1$
#1800
b10101010 #
b10101010 '
0$
#1850
b10001100 !
b10001100 (
b1000110011111001110001101100010110101010 +
1$
#1900
b11100101 #
b11100101 '
0$
#1950
b11111001 !
b11111001 (
b1111100111000110110001011010101011100101 +
1$
#2000
b1110111 #
b1110111 '
0$
#2050
b11000110 !
b11000110 (
b1100011011000101101010101110010101110111 +
1$
#2100
b10010 #
b10010 '
0$
#2150
b11000101 !
b11000101 (
b1100010110101010111001010111011100010010 +
1$
#2200
b10001111 #
b10001111 '
0$
#2250
b10101010 !
b10101010 (
b1010101011100101011101110001001010001111 +
1$
#2300
b11110010 #
b11110010 '
0$
#2350
b11100101 !
b11100101 (
b1110010101110111000100101000111111110010 +
1$
#2400
b11001110 #
b11001110 '
0$
#2450
b1110111 !
b1110111 (
b111011100010010100011111111001011001110 +
1$
#2500
b11101000 #
b11101000 '
0$
#2550
b10010 !
b10010 (
b1001010001111111100101100111011101000 +
1$
#2600
b11000101 #
b11000101 '
0$
#2650
b10001111 !
b10001111 (
b1000111111110010110011101110100011000101 +
1$
#2700
b1011100 #
b1011100 '
0$
#2750
b11110010 !
b11110010 (
b1111001011001110111010001100010101011100 +
1$
#2800
b10111101 #
b10111101 '
0$
#2850
b11001110 !
b11001110 (
b1100111011101000110001010101110010111101 +
1$
#2900
b101101 #
b101101 '
0$
#2950
b11101000 !
b11101000 (
b1110100011000101010111001011110100101101 +
1$
#3000
b1100101 #
b1100101 '
0$
#3050
b11000101 !
b11000101 (
b1100010101011100101111010010110101100101 +
1$
#3100
b1100011 #
b1100011 '
0$
#3150
b1011100 !
b1011100 (
b101110010111101001011010110010101100011 +
1$
#3200
b1010 #
b1010 '
0$
#3250
b10111101 !
b10111101 (
b1011110100101101011001010110001100001010 +
1$
#3300
b10000000 #
b10000000 '
0$
#3350
b101101 !
b101101 (
b10110101100101011000110000101010000000 +
1$
#3400
b100000 #
b100000 '
0$
#3450
b1100101 !
b1100101 (
b110010101100011000010101000000000100000 +
1$
#3500
b10101010 #
b10101010 '
0$
#3550
b1100011 !
b1100011 (
b110001100001010100000000010000010101010 +
1$
#3600
b10011101 #
b10011101 '
0$
#3650
b1010 !
b1010 (
b101010000000001000001010101010011101 +
1$
#3700
b10010110 #
b10010110 '
0$
#3750
b10000000 !
b10000000 (
b1000000000100000101010101001110110010110 +
1$
#3800
b10011 #
b10011 '
0$
#3850
b100000 !
b100000 (
b10000010101010100111011001011000010011 +
1$
#3900
b1101 #
b1101 '
0$
#3950
b10101010 !
b10101010 (
b1010101010011101100101100001001100001101 +
1$
