chapter4/counter/Counter.sv
`ifndef __COUNTER_SV__
`define __COUNTER_SV__

module Counter #(
    parameter int unsigned M    = 100,
    parameter type         dw_t = logic [$clog2(M) - 1 : 0]
) (
    input  logic clk,
    input  logic rst_n,
    input  logic en,
    output dw_t  cnt,
    output logic co
);

  dw_t cnt_inc;

  always_comb begin
    cnt_inc = (cnt < M - 1) ? cnt + 1'b1 : '0;
    co = en & (cnt == M - 1);
  end

  always_ff @(posedge clk, negedge rst_n) begin
    if (!rst_n) cnt <= '0;
    else if (en) cnt <= cnt_inc;
  end

endmodule

`endif

chapter4/counter/TestCounter.sv
`timescale 1ns / 100ps
`include "./Counter.sv"

`default_nettype none

module TestCounter;
  initial begin
    $dumpfile("TestCounter.vcd");
    $dumpvars(0, TestCounter);
  end

  logic clk = 1'b0;
  logic rst_n = 1'b0;
  initial forever #5 clk = ~clk;
  initial #35 rst_n = 1'b1;
  initial #2000 $finish;

  logic en;
  initial begin
    en = 1'b1;
    #100 en = 1'b0;
    #100 en = 1'b1;
  end

  localparam integer M = 32;
  logic [$clog2(M) - 1 : 0] cnt;
  logic co;
  Counter #(M) theCnt (
      .clk  (clk),
      .rst_n(rst_n),
      .en   (en),
      .cnt  (cnt),
      .co   (co)
  );

  initial if (co) assert (cnt == M - 1);

endmodule

chapter4/counter/TestCounter.vcd
$date
	Mon Dec 16 17:30:33 2024
$end
$version
	Icarus Verilog
$end
$timescale
	100ps
$end
$scope module TestCounter $end
$var wire 1 ! co $end
$var wire 5 " cnt [4:0] $end
$var parameter 32 # M $end
$var reg 1 $ clk $end
$var reg 1 % en $end
$var reg 1 & rst_n $end
$scope module theCnt $end
$var wire 1 $ clk $end
$var wire 1 ! co $end
$var wire 1 % en $end
$var wire 1 & rst_n $end
$var wire 5 ' cnt_inc [4:0] $end
$var parameter 32 ( M $end
$var reg 5 ) cnt [4:0] $end
$upscope $end
$upscope $end
$enddefinitions $end
$comment Show the parameter values. $end
$dumpall
b100000 (
b100000 #
$end
#0
$dumpvars
bx )
bx '
0&
1%
0$
bx "
x!
$end
#50
0!
b1 '
b0 "
b0 )
1$
#100
0$
#150
1$
#200
0$
#250
1$
#300
0$
#350
b10 '
b1 "
b1 )
1$
1&
#400
0$
#450
b11 '
b10 "
b10 )
1$
#500
0$
#550
b100 '
b11 "
b11 )
1$
#600
0$
#650
b101 '
b100 "
b100 )
1$
#700
0$
#750
b110 '
b101 "
b101 )
1$
#800
0$
#850
b111 '
b110 "
b110 )
1$
#900
0$
#950
b1000 '
b111 "
b111 )
1$
#1000
0$
0%
#1050
1$
#1100
0$
#1150
1$
#1200
0$
#1250
1$
#1300
0$
#1350
1$
#1400
0$
#1450
1$
#1500
0$
#1550
1$
#1600
0$
#1650
1$
#1700
0$
#1750
1$
#1800
0$
#1850
1$
#1900
0$
#1950
1$
#2000
0$
1%
#2050
b1001 '
b1000 "
b1000 )
1$
#2100
0$
#2150
b1010 '
b1001 "
b1001 )
1$
#2200
0$
#2250
b1011 '
b1010 "
b1010 )
1$
#2300
0$
#2350
b1100 '
b1011 "
b1011 )
1$
#2400
0$
#2450
b1101 '
b1100 "
b1100 )
1$
#2500
0$
#2550
b1110 '
b1101 "
b1101 )
1$
#2600
0$
#2650
b1111 '
b1110 "
b1110 )
1$
#2700
0$
#2750
b10000 '
b1111 "
b1111 )
1$
#2800
0$
#2850
b10001 '
b10000 "
b10000 )
1$
#2900
0$
#2950
b10010 '
b10001 "
b10001 )
1$
#3000
0$
#3050
b10011 '
b10010 "
b10010 )
1$
#3100
0$
#3150
b10100 '
b10011 "
b10011 )
1$
#3200
0$
#3250
b10101 '
b10100 "
b10100 )
1$
#3300
0$
#3350
b10110 '
b10101 "
b10101 )
1$
#3400
0$
#3450
b10111 '
b10110 "
b10110 )
1$
#3500
0$
#3550
b11000 '
b10111 "
b10111 )
1$
#3600
0$
#3650
b11001 '
b11000 "
b11000 )
1$
#3700
0$
#3750
b11010 '
b11001 "
b11001 )
1$
#3800
0$
#3850
b11011 '
b11010 "
b11010 )
1$
#3900
0$
#3950
b11100 '
b11011 "
b11011 )
1$
#4000
0$
#4050
b11101 '
b11100 "
b11100 )
1$
#4100
0$
#4150
b11110 '
b11101 "
b11101 )
1$
#4200
0$
#4250
b11111 '
b11110 "
b11110 )
1$
#4300
0$
#4350
1!
b0 '
b11111 "
b11111 )
1$
#4400
0$
#4450
0!
b1 '
b0 "
b0 )
1$
#4500
0$
#4550
b10 '
b1 "
b1 )
1$
#4600
0$
#4650
b11 '
b10 "
b10 )
1$
#4700
0$
#4750
b100 '
b11 "
b11 )
1$
#4800
0$
#4850
b101 '
b100 "
b100 )
1$
#4900
0$
#4950
b110 '
b101 "
b101 )
1$
#5000
0$
#5050
b111 '
b110 "
b110 )
1$
#5100
0$
#5150
b1000 '
b111 "
b111 )
1$
#5200
0$
#5250
b1001 '
b1000 "
b1000 )
1$
#5300
0$
#5350
b1010 '
b1001 "
b1001 )
1$
#5400
0$
#5450
b1011 '
b1010 "
b1010 )
1$
#5500
0$
#5550
b1100 '
b1011 "
b1011 )
1$
#5600
0$
#5650
b1101 '
b1100 "
b1100 )
1$
#5700
0$
#5750
b1110 '
b1101 "
b1101 )
1$
#5800
0$
#5850
b1111 '
b1110 "
b1110 )
1$
#5900
0$
#5950
b10000 '
b1111 "
b1111 )
1$
#6000
0$
#6050
b10001 '
b10000 "
b10000 )
1$
#6100
0$
#6150
b10010 '
b10001 "
b10001 )
1$
#6200
0$
#6250
b10011 '
b10010 "
b10010 )
1$
#6300
0$
#6350
b10100 '
b10011 "
b10011 )
1$
#6400
0$
#6450
b10101 '
b10100 "
b10100 )
1$
#6500
0$
#6550
b10110 '
b10101 "
b10101 )
1$
#6600
0$
#6650
b10111 '
b10110 "
b10110 )
1$
#6700
0$
#6750
b11000 '
b10111 "
b10111 )
1$
#6800
0$
#6850
b11001 '
b11000 "
b11000 )
1$
#6900
0$
#6950
b11010 '
b11001 "
b11001 )
1$
#7000
0$
#7050
b11011 '
b11010 "
b11010 )
1$
#7100
0$
#7150
b11100 '
b11011 "
b11011 )
1$
#7200
0$
#7250
b11101 '
b11100 "
b11100 )
1$
#7300
0$
#7350
b11110 '
b11101 "
b11101 )
1$
#7400
0$
#7450
b11111 '
b11110 "
b11110 )
1$
#7500
0$
#7550
1!
b0 '
b11111 "
b11111 )
1$
#7600
0$
#7650
0!
b1 '
b0 "
b0 )
1$
#7700
0$
#7750
b10 '
b1 "
b1 )
1$
#7800
0$
#7850
b11 '
b10 "
b10 )
1$
#7900
0$
#7950
b100 '
b11 "
b11 )
1$
#8000
0$
#8050
b101 '
b100 "
b100 )
1$
#8100
0$
#8150
b110 '
b101 "
b101 )
1$
#8200
0$
#8250
b111 '
b110 "
b110 )
1$
#8300
0$
#8350
b1000 '
b111 "
b111 )
1$
#8400
0$
#8450
b1001 '
b1000 "
b1000 )
1$
#8500
0$
#8550
b1010 '
b1001 "
b1001 )
1$
#8600
0$
#8650
b1011 '
b1010 "
b1010 )
1$
#8700
0$
#8750
b1100 '
b1011 "
b1011 )
1$
#8800
0$
#8850
b1101 '
b1100 "
b1100 )
1$
#8900
0$
#8950
b1110 '
b1101 "
b1101 )
1$
#9000
0$
#9050
b1111 '
b1110 "
b1110 )
1$
#9100
0$
#9150
b10000 '
b1111 "
b1111 )
1$
#9200
0$
#9250
b10001 '
b10000 "
b10000 )
1$
#9300
0$
#9350
b10010 '
b10001 "
b10001 )
1$
#9400
0$
#9450
b10011 '
b10010 "
b10010 )
1$
#9500
0$
#9550
b10100 '
b10011 "
b10011 )
1$
#9600
0$
#9650
b10101 '
b10100 "
b10100 )
1$
#9700
0$
#9750
b10110 '
b10101 "
b10101 )
1$
#9800
0$
#9850
b10111 '
b10110 "
b10110 )
1$
#9900
0$
#9950
b11000 '
b10111 "
b10111 )
1$
#10000
0$
#10050
b11001 '
b11000 "
b11000 )
1$
#10100
0$
#10150
b11010 '
b11001 "
b11001 )
1$
#10200
0$
#10250
b11011 '
b11010 "
b11010 )
1$
#10300
0$
#10350
b11100 '
b11011 "
b11011 )
1$
#10400
0$
#10450
b11101 '
b11100 "
b11100 )
1$
#10500
0$
#10550
b11110 '
b11101 "
b11101 )
1$
#10600
0$
#10650
b11111 '
b11110 "
b11110 )
1$
#10700
0$
#10750
1!
b0 '
b11111 "
b11111 )
1$
#10800
0$
#10850
0!
b1 '
b0 "
b0 )
1$
#10900
0$
#10950
b10 '
b1 "
b1 )
1$
#11000
0$
#11050
b11 '
b10 "
b10 )
1$
#11100
0$
#11150
b100 '
b11 "
b11 )
1$
#11200
0$
#11250
b101 '
b100 "
b100 )
1$
#11300
0$
#11350
b110 '
b101 "
b101 )
1$
#11400
0$
#11450
b111 '
b110 "
b110 )
1$
#11500
0$
#11550
b1000 '
b111 "
b111 )
1$
#11600
0$
#11650
b1001 '
b1000 "
b1000 )
1$
#11700
0$
#11750
b1010 '
b1001 "
b1001 )
1$
#11800
0$
#11850
b1011 '
b1010 "
b1010 )
1$
#11900
0$
#11950
b1100 '
b1011 "
b1011 )
1$
#12000
0$
#12050
b1101 '
b1100 "
b1100 )
1$
#12100
0$
#12150
b1110 '
b1101 "
b1101 )
1$
#12200
0$
#12250
b1111 '
b1110 "
b1110 )
1$
#12300
0$
#12350
b10000 '
b1111 "
b1111 )
1$
#12400
0$
#12450
b10001 '
b10000 "
b10000 )
1$
#12500
0$
#12550
b10010 '
b10001 "
b10001 )
1$
#12600
0$
#12650
b10011 '
b10010 "
b10010 )
1$
#12700
0$
#12750
b10100 '
b10011 "
b10011 )
1$
#12800
0$
#12850
b10101 '
b10100 "
b10100 )
1$
#12900
0$
#12950
b10110 '
b10101 "
b10101 )
1$
#13000
0$
#13050
b10111 '
b10110 "
b10110 )
1$
#13100
0$
#13150
b11000 '
b10111 "
b10111 )
1$
#13200
0$
#13250
b11001 '
b11000 "
b11000 )
1$
#13300
0$
#13350
b11010 '
b11001 "
b11001 )
1$
#13400
0$
#13450
b11011 '
b11010 "
b11010 )
1$
#13500
0$
#13550
b11100 '
b11011 "
b11011 )
1$
#13600
0$
#13650
b11101 '
b11100 "
b11100 )
1$
#13700
0$
#13750
b11110 '
b11101 "
b11101 )
1$
#13800
0$
#13850
b11111 '
b11110 "
b11110 )
1$
#13900
0$
#13950
1!
b0 '
b11111 "
b11111 )
1$
#14000
0$
#14050
0!
b1 '
b0 "
b0 )
1$
#14100
0$
#14150
b10 '
b1 "
b1 )
1$
#14200
0$
#14250
b11 '
b10 "
b10 )
1$
#14300
0$
#14350
b100 '
b11 "
b11 )
1$
#14400
0$
#14450
b101 '
b100 "
b100 )
1$
#14500
0$
#14550
b110 '
b101 "
b101 )
1$
#14600
0$
#14650
b111 '
b110 "
b110 )
1$
#14700
0$
#14750
b1000 '
b111 "
b111 )
1$
#14800
0$
#14850
b1001 '
b1000 "
b1000 )
1$
#14900
0$
#14950
b1010 '
b1001 "
b1001 )
1$
#15000
0$
#15050
b1011 '
b1010 "
b1010 )
1$
#15100
0$
#15150
b1100 '
b1011 "
b1011 )
1$
#15200
0$
#15250
b1101 '
b1100 "
b1100 )
1$
#15300
0$
#15350
b1110 '
b1101 "
b1101 )
1$
#15400
0$
#15450
b1111 '
b1110 "
b1110 )
1$
#15500
0$
#15550
b10000 '
b1111 "
b1111 )
1$
#15600
0$
#15650
b10001 '
b10000 "
b10000 )
1$
#15700
0$
#15750
b10010 '
b10001 "
b10001 )
1$
#15800
0$
#15850
b10011 '
b10010 "
b10010 )
1$
#15900
0$
#15950
b10100 '
b10011 "
b10011 )
1$
#16000
0$
#16050
b10101 '
b10100 "
b10100 )
1$
#16100
0$
#16150
b10110 '
b10101 "
b10101 )
1$
#16200
0$
#16250
b10111 '
b10110 "
b10110 )
1$
#16300
0$
#16350
b11000 '
b10111 "
b10111 )
1$
#16400
0$
#16450
b11001 '
b11000 "
b11000 )
1$
#16500
0$
#16550
b11010 '
b11001 "
b11001 )
1$
#16600
0$
#16650
b11011 '
b11010 "
b11010 )
1$
#16700
0$
#16750
b11100 '
b11011 "
b11011 )
1$
#16800
0$
#16850
b11101 '
b11100 "
b11100 )
1$
#16900
0$
#16950
b11110 '
b11101 "
b11101 )
1$
#17000
0$
#17050
b11111 '
b11110 "
b11110 )
1$
#17100
0$
#17150
1!
b0 '
b11111 "
b11111 )
1$
#17200
0$
#17250
0!
b1 '
b0 "
b0 )
1$
#17300
0$
#17350
b10 '
b1 "
b1 )
1$
#17400
0$
#17450
b11 '
b10 "
b10 )
1$
#17500
0$
#17550
b100 '
b11 "
b11 )
1$
#17600
0$
#17650
b101 '
b100 "
b100 )
1$
#17700
0$
#17750
b110 '
b101 "
b101 )
1$
#17800
0$
#17850
b111 '
b110 "
b110 )
1$
#17900
0$
#17950
b1000 '
b111 "
b111 )
1$
#18000
0$
#18050
b1001 '
b1000 "
b1000 )
1$
#18100
0$
#18150
b1010 '
b1001 "
b1001 )
1$
#18200
0$
#18250
b1011 '
b1010 "
b1010 )
1$
#18300
0$
#18350
b1100 '
b1011 "
b1011 )
1$
#18400
0$
#18450
b1101 '
b1100 "
b1100 )
1$
#18500
0$
#18550
b1110 '
b1101 "
b1101 )
1$
#18600
0$
#18650
b1111 '
b1110 "
b1110 )
1$
#18700
0$
#18750
b10000 '
b1111 "
b1111 )
1$
#18800
0$
#18850
b10001 '
b10000 "
b10000 )
1$
#18900
0$
#18950
b10010 '
b10001 "
b10001 )
1$
#19000
0$
#19050
b10011 '
b10010 "
b10010 )
1$
#19100
0$
#19150
b10100 '
b10011 "
b10011 )
1$
#19200
0$
#19250
b10101 '
b10100 "
b10100 )
1$
#19300
0$
#19350
b10110 '
b10101 "
b10101 )
1$
#19400
0$
#19450
b10111 '
b10110 "
b10110 )
1$
#19500
0$
#19550
b11000 '
b10111 "
b10111 )
1$
#19600
0$
#19650
b11001 '
b11000 "
b11000 )
1$
#19700
0$
#19750
b11010 '
b11001 "
b11001 )
1$
#19800
0$
#19850
b11011 '
b11010 "
b11010 )
1$
#19900
0$
#19950
b11100 '
b11011 "
b11011 )
1$
